[{"Id":"0cd2afc9fa5640899a6c222cde567fd3","Expediente":"2026-00001","FechaIngreso":"\/Date(1772406663569)\/","RegistradoPor":"admin@refugio.com","Nombre":"LALA","Especie":"Gato","Raza":"Desconocida","EdadAprox":"9 meses","Sexo":"Hembra","Color":"Gris","MotivoIngreso":"Daño en garras","Temperamento":"Miedoso","NecesidadesMedicas":"Anestesia local","HistorialVacunas":"N/A","EstadoSaludIngreso":"El animal entra asustado y requiere tratamiento inicial en garras.","Rescatista":{"FullName":"Jose Alberto Gonzalez Aguilera","Phone":"83413256","Email":"jose2314ab@gmail.com"},"Tratamientos":[{"Id":"a53b4712fca246c9bb291ba2f2bbc333","Date":"\/Date(1772344800000)\/","Type":"Vacuna","MedicineId":"660dee58e99344879d4fafd6b846da81","MedicineName":"Ivermectina","Dose":"0.2 ml","Observations":"Mejoras en dolor del amimal","CaregiverEmail":"admin@refugio.com"},{"Id":"fb35f229669b4e3b85c405a8427bc1bf","Date":"\/Date(1772344800000)\/","Type":"Vacuna","MedicineId":"0296cd1ca44d45f181a75d2ccf987ff7","MedicineName":"Vacuna antirrábica","Dose":"1.2 ml","Observations":"Vacuna preventiva.","CaregiverEmail":"cuidador@refugio.com"}]},{"Id":"cfc2c14af56d4424821cd31906f0e1e8","Expediente":"2026-00002","FechaIngreso":"\/Date(1772408257641)\/","RegistradoPor":"admin@refugio.com","Nombre":"MISHA","Especie":"Gato","Raza":"Desconocida","EdadAprox":"12 meses","Sexo":"Hembra","Color":"negro","MotivoIngreso":"Dolor localizado en pata derecha","Temperamento":"Agresivo","NecesidadesMedicas":"Anestecia","HistorialVacunas":"N/A","EstadoSaludIngreso":"Gato negro entra con bastante agresividad","Rescatista":{"FullName":"Jose Alberto Gonzalez Aguilera","Phone":"83413256","Email":"jose2314ab@gmail.com"},"Tratamientos":[{"Id":"57922273d85a4b61b1f5fcc0b4518594","Date":"\/Date(1769925600000)\/","Type":"Medicamento","MedicineId":"90e8bfce6994441c9716c8afbf4ae85f","MedicineName":"Anestesia","Dose":"1.2","Observations":"Se aplica para poder revisar","CaregiverEmail":"admin@refugio.com"}]},{"Id":"041942f51e3f40fbaa206c01b3f4b438","Expediente":"2026-00003","FechaIngreso":"\/Date(1772408566421)\/","RegistradoPor":"admin@refugio.com","Nombre":"VACA","Especie":"Perro","Raza":"Stanford","EdadAprox":"6 meses","Sexo":"Macho","Color":"Negro y blanco","MotivoIngreso":"Perdida de colmillo","Temperamento":"Docil","NecesidadesMedicas":"Anestesia local","HistorialVacunas":"N/A","EstadoSaludIngreso":"Animal ingresa docil pero no deja revisar el area afectada","Rescatista":{"FullName":"Jose Alberto Gonzalez Aguilera","Phone":"83413256","Email":"jose2314ab@gmail.com"},"Tratamientos":[]}]